systembridge/__init__.py
systembridge/exceptions.py
systembridge/client/__init__.py
systembridge/client_websocket/__init__.py
systembridge/objects/__init__.py
systembridge/objects/base.py
systembridge/objects/battery.py
systembridge/objects/bluetooth.py
systembridge/objects/cpu.py
systembridge/objects/graphics.py
systembridge/objects/hardware_sensor.py
systembridge/objects/information.py
systembridge/objects/memory.py
systembridge/objects/network.py
systembridge/objects/os.py
systembridge/objects/processes.py
systembridge/objects/system.py
systembridge/objects/audio/__init__.py
systembridge/objects/audio/put.py
systembridge/objects/command/__init__.py
systembridge/objects/command/payload.py
systembridge/objects/command/response.py
systembridge/objects/display/__init__.py
systembridge/objects/display/put.py
systembridge/objects/events/__init__.py
systembridge/objects/filesystem/__init__.py
systembridge/objects/filesystem/file.py
systembridge/objects/keyboard/__init__.py
systembridge/objects/keyboard/payload.py
systembridge/objects/keyboard/response.py
systembridge/objects/open/__init__.py
systembridge/objects/open/payload.py
systembridge/objects/settings/__init__.py
systembridge/objects/settings/put.py
systembridge-2.3.1.dist-info/LICENSE
systembridge-2.3.1.dist-info/METADATA
systembridge-2.3.1.dist-info/WHEEL
systembridge-2.3.1.dist-info/top_level.txt
systembridge-2.3.1.dist-info/RECORD
