Metadata-Version: 2.1
Name: systembridge
Version: 2.3.1
Summary: Python package for connecting to System Bridge.
Home-page: https://github.com/timmo001/system-bridge-connector-py
Author: Aidan Timson (Timmo)
Author-email: contact@timmo.xyz
License: MIT
Keywords: system bridge connector
Platform: UNKNOWN
License-File: LICENSE
Requires-Dist: aiohttp (<4,>=3.7.4)
Requires-Dist: websockets (<11,>=9.1)
